autodev/__init__.py
autodev/adapters/__init__.py
autodev/adapters/abstract.py
autodev/adapters/github.py
autodev/config.py
autodev/entrypoints/__init__.py
autodev/entrypoints/cli.py
autodev/model.py
autodev/py.typed
autodev/services.py
autodev/version.py
autodev-0.0.1.dist-info/LICENSE
autodev-0.0.1.dist-info/WHEEL
autodev-0.0.1.dist-info/METADATA
autodev-0.0.1.dist-info/RECORD
